<annotation>
	<folder>VOC2007</folder>
	<filename>0000354_000001.jpg</filename>
	<path>G:\1\voc_m\JPEGImages\(672).jpg</path>
	<source>
		<database>Unknown</database>
	</source>
	<size>
		<width>640</width>
		<height>640</height>
		<depth>3</depth>
	</size>
	<segmented>0</segmented>
	<object>
		<name>Late_blight</name>
		<pose>Unspecified</pose>
		<truncated>0</truncated>
		<difficult>0</difficult>
		<bndbox>
			<xmin>277</xmin>
			<ymin>354</ymin>
			<xmax>343</xmax>
			<ymax>453</ymax>
		</bndbox>
	</object>
	<object>
		<name>Late_blight</name>
		<pose>Unspecified</pose>
		<truncated>0</truncated>
		<difficult>0</difficult>
		<bndbox>
			<xmin>300</xmin>
			<ymin>205</ymin>
			<xmax>356</xmax>
			<ymax>268</ymax>
		</bndbox>
	</object>
	<object>
		<name>Late_blight</name>
		<pose>Unspecified</pose>
		<truncated>0</truncated>
		<difficult>0</difficult>
		<bndbox>
			<xmin>360</xmin>
			<ymin>236</ymin>
			<xmax>395</xmax>
			<ymax>279</ymax>
		</bndbox>
	</object>
	<object>
		<name>Late_blight</name>
		<pose>Unspecified</pose>
		<truncated>0</truncated>
		<difficult>0</difficult>
		<bndbox>
			<xmin>359</xmin>
			<ymin>257</ymin>
			<xmax>522</xmax>
			<ymax>411</ymax>
		</bndbox>
	</object>
	<object>
		<name>Late_blight</name>
		<pose>Unspecified</pose>
		<truncated>0</truncated>
		<difficult>0</difficult>
		<bndbox>
			<xmin>275</xmin>
			<ymin>303</ymin>
			<xmax>296</xmax>
			<ymax>322</ymax>
		</bndbox>
	</object>
	<object>
		<name>Late_blight</name>
		<pose>Unspecified</pose>
		<truncated>0</truncated>
		<difficult>0</difficult>
		<bndbox>
			<xmin>402</xmin>
			<ymin>389</ymin>
			<xmax>444</xmax>
			<ymax>431</ymax>
		</bndbox>
	</object>
</annotation>