<annotation>
	<folder>VOC2007</folder>
	<filename>0000072_000001.jpg</filename>
	<path>E:\1\voc_m\JPEGImages\(1160).jpg</path>
	<source>
		<database>Unknown</database>
	</source>
	<size>
		<width>640</width>
		<height>640</height>
		<depth>3</depth>
	</size>
	<segmented>0</segmented>
	<object>
		<name>Leaf_Mold</name>
		<pose>Unspecified</pose>
		<truncated>0</truncated>
		<difficult>0</difficult>
		<bndbox>
			<xmin>238</xmin>
			<ymin>279</ymin>
			<xmax>309</xmax>
			<ymax>356</ymax>
		</bndbox>
	</object>
	<object>
		<name>Leaf_Mold</name>
		<pose>Unspecified</pose>
		<truncated>0</truncated>
		<difficult>0</difficult>
		<bndbox>
			<xmin>282</xmin>
			<ymin>413</ymin>
			<xmax>436</xmax>
			<ymax>548</ymax>
		</bndbox>
	</object>
	<object>
		<name>Leaf_Mold</name>
		<pose>Unspecified</pose>
		<truncated>0</truncated>
		<difficult>0</difficult>
		<bndbox>
			<xmin>305</xmin>
			<ymin>299</ymin>
			<xmax>374</xmax>
			<ymax>367</ymax>
		</bndbox>
	</object>
</annotation>