<annotation>
	<folder>JPEGImages</folder>
	<filename>Early_blight	(958).JPG</filename>
	<path>C:\Users\xie rong chang\Desktop\Tomato\JPEGImages\Early_blight	(958).JPG</path>
	<source>
		<database>Unknown</database>
	</source>
	<size>
		<width>256</width>
		<height>256</height>
		<depth>3</depth>
	</size>
	<segmented>0</segmented>
	<object>
		<name>Early_blight</name>
		<pose>Unspecified</pose>
		<truncated>0</truncated>
		<difficult>0</difficult>
		<bndbox>
			<xmin>105</xmin>
			<ymin>135</ymin>
			<xmax>117</xmax>
			<ymax>145</ymax>
		</bndbox>
	</object>
	<object>
		<name>Early_blight</name>
		<pose>Unspecified</pose>
		<truncated>0</truncated>
		<difficult>0</difficult>
		<bndbox>
			<xmin>127</xmin>
			<ymin>134</ymin>
			<xmax>157</xmax>
			<ymax>147</ymax>
		</bndbox>
	</object>
</annotation>
