<annotation>
	<folder>JPEGImages</folder>
	<filename>Leaf_Mold (562)_000005.jpg</filename>
	<path>E:\Tomato\JPEGImages\Leaf_Mold (562).JPG</path>
	<source>
		<database>Unknown</database>
	</source>
	<size>
		<width>256</width>
		<height>256</height>
		<depth>3</depth>
	</size>
	<segmented>0</segmented>
	<object>
		<name>Leaf_Mold</name>
		<pose>Unspecified</pose>
		<truncated>0</truncated>
		<difficult>0</difficult>
		<bndbox>
			<xmin>108</xmin>
			<ymin>21</ymin>
			<xmax>137</xmax>
			<ymax>42</ymax>
		</bndbox>
	</object>
	<object>
		<name>Leaf_Mold</name>
		<pose>Unspecified</pose>
		<truncated>0</truncated>
		<difficult>0</difficult>
		<bndbox>
			<xmin>56</xmin>
			<ymin>30</ymin>
			<xmax>74</xmax>
			<ymax>46</ymax>
		</bndbox>
	</object>
	<object>
		<name>Leaf_Mold</name>
		<pose>Unspecified</pose>
		<truncated>0</truncated>
		<difficult>0</difficult>
		<bndbox>
			<xmin>40</xmin>
			<ymin>71</ymin>
			<xmax>63</xmax>
			<ymax>92</ymax>
		</bndbox>
	</object>
	<object>
		<name>Leaf_Mold</name>
		<pose>Unspecified</pose>
		<truncated>0</truncated>
		<difficult>0</difficult>
		<bndbox>
			<xmin>29</xmin>
			<ymin>29</ymin>
			<xmax>256</xmax>
			<ymax>256</ymax>
		</bndbox>
	</object>
</annotation>