<annotation>
	<folder>JPEGImages</folder>
	<filename>Leaf_Mold (9)_000005.jpg</filename>
	<path>C:\Users\xie rong chang\Desktop\Tomato\JPEGImages\Leaf_Mold (9).JPG</path>
	<source>
		<database>Unknown</database>
	</source>
	<size>
		<width>256</width>
		<height>256</height>
		<depth>3</depth>
	</size>
	<segmented>0</segmented>
	<object>
		<name>Leaf_Mold</name>
		<pose>Unspecified</pose>
		<truncated>0</truncated>
		<difficult>0</difficult>
		<bndbox>
			<xmin>63</xmin>
			<ymin>79</ymin>
			<xmax>148</xmax>
			<ymax>223</ymax>
		</bndbox>
	</object>
	<object>
		<name>Leaf_Mold</name>
		<pose>Unspecified</pose>
		<truncated>0</truncated>
		<difficult>0</difficult>
		<bndbox>
			<xmin>185</xmin>
			<ymin>142</ymin>
			<xmax>207</xmax>
			<ymax>175</ymax>
		</bndbox>
	</object>
</annotation>