<annotation>
	<folder>JPEGImages</folder>
	<filename>1(400)_000001.jpg</filename>
	<path>G:\1\voc_m\JPEGImages\(400).jpg</path>
	<source>
		<database>Unknown</database>
	</source>
	<size>
		<width>640</width>
		<height>640</height>
		<depth>3</depth>
	</size>
	<segmented>0</segmented>
	<object>
		<name>Early_blight</name>
		<pose>Unspecified</pose>
		<truncated>0</truncated>
		<difficult>0</difficult>
		<bndbox>
			<xmin>364</xmin>
			<ymin>381</ymin>
			<xmax>449</xmax>
			<ymax>483</ymax>
		</bndbox>
	</object>
	<object>
		<name>Early_blight</name>
		<pose>Unspecified</pose>
		<truncated>0</truncated>
		<difficult>0</difficult>
		<bndbox>
			<xmin>217</xmin>
			<ymin>359</ymin>
			<xmax>410</xmax>
			<ymax>574</ymax>
		</bndbox>
	</object>
	<object>
		<name>Early_blight</name>
		<pose>Unspecified</pose>
		<truncated>0</truncated>
		<difficult>0</difficult>
		<bndbox>
			<xmin>42</xmin>
			<ymin>94</ymin>
			<xmax>302</xmax>
			<ymax>378</ymax>
		</bndbox>
	</object>
	<object>
		<name>Early_blight</name>
		<pose>Unspecified</pose>
		<truncated>0</truncated>
		<difficult>0</difficult>
		<bndbox>
			<xmin>383</xmin>
			<ymin>171</ymin>
			<xmax>429</xmax>
			<ymax>214</ymax>
		</bndbox>
	</object>
	<object>
		<name>Early_blight</name>
		<pose>Unspecified</pose>
		<truncated>0</truncated>
		<difficult>0</difficult>
		<bndbox>
			<xmin>455</xmin>
			<ymin>118</ymin>
			<xmax>518</xmax>
			<ymax>173</ymax>
		</bndbox>
	</object>
	<object>
		<name>Early_blight</name>
		<pose>Unspecified</pose>
		<truncated>0</truncated>
		<difficult>0</difficult>
		<bndbox>
			<xmin>405</xmin>
			<ymin>104</ymin>
			<xmax>439</xmax>
			<ymax>137</ymax>
		</bndbox>
	</object>
</annotation>