<annotation>
	<folder>JPEGImages</folder>
	<filename>1(48)_000003.jpg</filename>
	<path>C:\Users\xie rong chang\Desktop\voc_m\JPEGImages\(48).jpg</path>
	<source>
		<database>Unknown</database>
	</source>
	<size>
		<width>640</width>
		<height>640</height>
		<depth>3</depth>
	</size>
	<segmented>0</segmented>
	<object>
		<name>Early_blight</name>
		<pose>Unspecified</pose>
		<truncated>0</truncated>
		<difficult>0</difficult>
		<bndbox>
			<xmin>171</xmin>
			<ymin>119</ymin>
			<xmax>359</xmax>
			<ymax>358</ymax>
		</bndbox>
	</object>
	<object>
		<name>Early_blight</name>
		<pose>Unspecified</pose>
		<truncated>0</truncated>
		<difficult>0</difficult>
		<bndbox>
			<xmin>342</xmin>
			<ymin>339</ymin>
			<xmax>388</xmax>
			<ymax>445</ymax>
		</bndbox>
	</object>
	<object>
		<name>Early_blight</name>
		<pose>Unspecified</pose>
		<truncated>0</truncated>
		<difficult>0</difficult>
		<bndbox>
			<xmin>280</xmin>
			<ymin>371</ymin>
			<xmax>299</xmax>
			<ymax>387</ymax>
		</bndbox>
	</object>
	<object>
		<name>Early_blight</name>
		<pose>Unspecified</pose>
		<truncated>0</truncated>
		<difficult>0</difficult>
		<bndbox>
			<xmin>305</xmin>
			<ymin>553</ymin>
			<xmax>335</xmax>
			<ymax>576</ymax>
		</bndbox>
	</object>
	<object>
		<name>Early_blight</name>
		<pose>Unspecified</pose>
		<truncated>0</truncated>
		<difficult>0</difficult>
		<bndbox>
			<xmin>417</xmin>
			<ymin>393</ymin>
			<xmax>478</xmax>
			<ymax>480</ymax>
		</bndbox>
	</object>
	<object>
		<name>Early_blight</name>
		<pose>Unspecified</pose>
		<truncated>0</truncated>
		<difficult>0</difficult>
		<bndbox>
			<xmin>416</xmin>
			<ymin>201</ymin>
			<xmax>453</xmax>
			<ymax>225</ymax>
		</bndbox>
	</object>
	<object>
		<name>Early_blight</name>
		<pose>Unspecified</pose>
		<truncated>0</truncated>
		<difficult>0</difficult>
		<bndbox>
			<xmin>424</xmin>
			<ymin>201</ymin>
			<xmax>482</xmax>
			<ymax>256</ymax>
		</bndbox>
	</object>
	<object>
		<name>Early_blight</name>
		<pose>Unspecified</pose>
		<truncated>0</truncated>
		<difficult>0</difficult>
		<bndbox>
			<xmin>422</xmin>
			<ymin>155</ymin>
			<xmax>436</xmax>
			<ymax>170</ymax>
		</bndbox>
	</object>
	<object>
		<name>Early_blight</name>
		<pose>Unspecified</pose>
		<truncated>0</truncated>
		<difficult>0</difficult>
		<bndbox>
			<xmin>451</xmin>
			<ymin>153</ymin>
			<xmax>470</xmax>
			<ymax>174</ymax>
		</bndbox>
	</object>
</annotation>