<annotation>
	<folder>JPEGImages</folder>
	<filename>(672).jpg</filename>
	<path>G:\1\voc_m\JPEGImages\(672).jpg</path>
	<source>
		<database>Unknown</database>
	</source>
	<size>
		<width>640</width>
		<height>640</height>
		<depth>3</depth>
	</size>
	<segmented>0</segmented>
	<object>
		<name>healthy</name>
		<pose>Unspecified</pose>
		<truncated>1</truncated>
		<difficult>0</difficult>
		<bndbox>
			<xmin>1</xmin>
			<ymin>212</ymin>
			<xmax>265</xmax>
			<ymax>446</ymax>
		</bndbox>
	</object>
	<object>
		<name>Late_blight</name>
		<pose>Unspecified</pose>
		<truncated>0</truncated>
		<difficult>0</difficult>
		<bndbox>
			<xmin>242</xmin>
			<ymin>188</ymin>
			<xmax>301</xmax>
			<ymax>300</ymax>
		</bndbox>
	</object>
	<object>
		<name>Late_blight</name>
		<pose>Unspecified</pose>
		<truncated>0</truncated>
		<difficult>0</difficult>
		<bndbox>
			<xmin>311</xmin>
			<ymin>406</ymin>
			<xmax>367</xmax>
			<ymax>474</ymax>
		</bndbox>
	</object>
	<object>
		<name>Late_blight</name>
		<pose>Unspecified</pose>
		<truncated>0</truncated>
		<difficult>0</difficult>
		<bndbox>
			<xmin>376</xmin>
			<ymin>377</ymin>
			<xmax>410</xmax>
			<ymax>424</ymax>
		</bndbox>
	</object>
	<object>
		<name>Late_blight</name>
		<pose>Unspecified</pose>
		<truncated>0</truncated>
		<difficult>0</difficult>
		<bndbox>
			<xmin>362</xmin>
			<ymin>214</ymin>
			<xmax>534</xmax>
			<ymax>369</ymax>
		</bndbox>
	</object>
	<object>
		<name>Late_blight</name>
		<pose>Unspecified</pose>
		<truncated>0</truncated>
		<difficult>0</difficult>
		<bndbox>
			<xmin>256</xmin>
			<ymin>351</ymin>
			<xmax>278</xmax>
			<ymax>370</ymax>
		</bndbox>
	</object>
	<object>
		<name>Late_blight</name>
		<pose>Unspecified</pose>
		<truncated>0</truncated>
		<difficult>0</difficult>
		<bndbox>
			<xmin>384</xmin>
			<ymin>183</ymin>
			<xmax>427</xmax>
			<ymax>227</ymax>
		</bndbox>
	</object>
</annotation>
