<annotation>
	<folder>JPEGImages</folder>
	<filename>1(767)_000002.jpg</filename>
	<path>E:\1\voc_m\JPEGImages\(767).jpg</path>
	<source>
		<database>Unknown</database>
	</source>
	<size>
		<width>640</width>
		<height>640</height>
		<depth>3</depth>
	</size>
	<segmented>0</segmented>
	<object>
		<name>healthy</name>
		<pose>Unspecified</pose>
		<truncated>0</truncated>
		<difficult>0</difficult>
		<bndbox>
			<xmin>187</xmin>
			<ymin>141</ymin>
			<xmax>519</xmax>
			<ymax>483</ymax>
		</bndbox>
	</object>
	<object>
		<name>Late_blight</name>
		<pose>Unspecified</pose>
		<truncated>0</truncated>
		<difficult>0</difficult>
		<bndbox>
			<xmin>307</xmin>
			<ymin>55</ymin>
			<xmax>538</xmax>
			<ymax>277</ymax>
		</bndbox>
	</object>
	<object>
		<name>Late_blight</name>
		<pose>Unspecified</pose>
		<truncated>0</truncated>
		<difficult>0</difficult>
		<bndbox>
			<xmin>247</xmin>
			<ymin>151</ymin>
			<xmax>331</xmax>
			<ymax>210</ymax>
		</bndbox>
	</object>
	<object>
		<name>Late_blight</name>
		<pose>Unspecified</pose>
		<truncated>0</truncated>
		<difficult>0</difficult>
		<bndbox>
			<xmin>180</xmin>
			<ymin>195</ymin>
			<xmax>274</xmax>
			<ymax>278</ymax>
		</bndbox>
	</object>
	<object>
		<name>Late_blight</name>
		<pose>Unspecified</pose>
		<truncated>0</truncated>
		<difficult>0</difficult>
		<bndbox>
			<xmin>141</xmin>
			<ymin>191</ymin>
			<xmax>191</xmax>
			<ymax>239</ymax>
		</bndbox>
	</object>
</annotation>