<annotation>
	<folder>JPEGImages</folder>
	<filename>1(862)_000003.jpg</filename>
	<path>E:\1\voc_m\JPEGImages\(862).jpg</path>
	<source>
		<database>Unknown</database>
	</source>
	<size>
		<width>640</width>
		<height>640</height>
		<depth>3</depth>
	</size>
	<segmented>0</segmented>
	<object>
		<name>Leaf_Mold</name>
		<pose>Unspecified</pose>
		<truncated>0</truncated>
		<difficult>0</difficult>
		<bndbox>
			<xmin>384</xmin>
			<ymin>262</ymin>
			<xmax>430</xmax>
			<ymax>321</ymax>
		</bndbox>
	</object>
	<object>
		<name>Leaf_Mold</name>
		<pose>Unspecified</pose>
		<truncated>0</truncated>
		<difficult>0</difficult>
		<bndbox>
			<xmin>323</xmin>
			<ymin>308</ymin>
			<xmax>423</xmax>
			<ymax>384</ymax>
		</bndbox>
	</object>
	<object>
		<name>Leaf_Mold</name>
		<pose>Unspecified</pose>
		<truncated>0</truncated>
		<difficult>0</difficult>
		<bndbox>
			<xmin>395</xmin>
			<ymin>274</ymin>
			<xmax>516</xmax>
			<ymax>430</ymax>
		</bndbox>
	</object>
	<object>
		<name>Leaf_Mold</name>
		<pose>Unspecified</pose>
		<truncated>0</truncated>
		<difficult>0</difficult>
		<bndbox>
			<xmin>334</xmin>
			<ymin>254</ymin>
			<xmax>359</xmax>
			<ymax>284</ymax>
		</bndbox>
	</object>
	<object>
		<name>Leaf_Mold</name>
		<pose>Unspecified</pose>
		<truncated>0</truncated>
		<difficult>0</difficult>
		<bndbox>
			<xmin>469</xmin>
			<ymin>166</ymin>
			<xmax>514</xmax>
			<ymax>216</ymax>
		</bndbox>
	</object>
</annotation>