<annotation>
	<folder>JPEGImages</folder>
	<filename>(877).jpg</filename>
	<path>E:\1\voc_m\JPEGImages\(877).jpg</path>
	<source>
		<database>Unknown</database>
	</source>
	<size>
		<width>640</width>
		<height>640</height>
		<depth>3</depth>
	</size>
	<segmented>0</segmented>
	<object>
		<name>Leaf_Mold</name>
		<pose>Unspecified</pose>
		<truncated>0</truncated>
		<difficult>0</difficult>
		<bndbox>
			<xmin>349</xmin>
			<ymin>378</ymin>
			<xmax>393</xmax>
			<ymax>416</ymax>
		</bndbox>
	</object>
	<object>
		<name>Leaf_Mold</name>
		<pose>Unspecified</pose>
		<truncated>0</truncated>
		<difficult>0</difficult>
		<bndbox>
			<xmin>402</xmin>
			<ymin>375</ymin>
			<xmax>428</xmax>
			<ymax>403</ymax>
		</bndbox>
	</object>
	<object>
		<name>Leaf_Mold</name>
		<pose>Unspecified</pose>
		<truncated>0</truncated>
		<difficult>0</difficult>
		<bndbox>
			<xmin>304</xmin>
			<ymin>294</ymin>
			<xmax>343</xmax>
			<ymax>356</ymax>
		</bndbox>
	</object>
	<object>
		<name>Leaf_Mold</name>
		<pose>Unspecified</pose>
		<truncated>0</truncated>
		<difficult>0</difficult>
		<bndbox>
			<xmin>353</xmin>
			<ymin>250</ymin>
			<xmax>404</xmax>
			<ymax>335</ymax>
		</bndbox>
	</object>
	<object>
		<name>Leaf_Mold</name>
		<pose>Unspecified</pose>
		<truncated>0</truncated>
		<difficult>0</difficult>
		<bndbox>
			<xmin>318</xmin>
			<ymin>203</ymin>
			<xmax>346</xmax>
			<ymax>230</ymax>
		</bndbox>
	</object>
	<object>
		<name>Leaf_Mold</name>
		<pose>Unspecified</pose>
		<truncated>0</truncated>
		<difficult>0</difficult>
		<bndbox>
			<xmin>265</xmin>
			<ymin>126</ymin>
			<xmax>394</xmax>
			<ymax>183</ymax>
		</bndbox>
	</object>
	<object>
		<name>Leaf_Mold</name>
		<pose>Unspecified</pose>
		<truncated>0</truncated>
		<difficult>0</difficult>
		<bndbox>
			<xmin>181</xmin>
			<ymin>204</ymin>
			<xmax>206</xmax>
			<ymax>230</ymax>
		</bndbox>
	</object>
	<object>
		<name>Leaf_Mold</name>
		<pose>Unspecified</pose>
		<truncated>0</truncated>
		<difficult>0</difficult>
		<bndbox>
			<xmin>211</xmin>
			<ymin>246</ymin>
			<xmax>255</xmax>
			<ymax>287</ymax>
		</bndbox>
	</object>
</annotation>
