<annotation>
	<folder>JPEGImages</folder>
	<filename>(9).jpg</filename>
	<path>C:\Users\xie rong chang\Desktop\voc_m\JPEGImages\(9).jpg</path>
	<source>
		<database>Unknown</database>
	</source>
	<size>
		<width>640</width>
		<height>640</height>
		<depth>3</depth>
	</size>
	<segmented>0</segmented>
	<object>
		<name>Early_blight</name>
		<pose>Unspecified</pose>
		<truncated>0</truncated>
		<difficult>0</difficult>
		<bndbox>
			<xmin>388</xmin>
			<ymin>293</ymin>
			<xmax>494</xmax>
			<ymax>467</ymax>
		</bndbox>
	</object>
	<object>
		<name>Early_blight</name>
		<pose>Unspecified</pose>
		<truncated>0</truncated>
		<difficult>0</difficult>
		<bndbox>
			<xmin>534</xmin>
			<ymin>154</ymin>
			<xmax>575</xmax>
			<ymax>233</ymax>
		</bndbox>
	</object>
	<object>
		<name>Early_blight</name>
		<pose>Unspecified</pose>
		<truncated>0</truncated>
		<difficult>0</difficult>
		<bndbox>
			<xmin>390</xmin>
			<ymin>218</ymin>
			<xmax>443</xmax>
			<ymax>265</ymax>
		</bndbox>
	</object>
	<object>
		<name>Early_blight</name>
		<pose>Unspecified</pose>
		<truncated>0</truncated>
		<difficult>0</difficult>
		<bndbox>
			<xmin>18</xmin>
			<ymin>115</ymin>
			<xmax>166</xmax>
			<ymax>334</ymax>
		</bndbox>
	</object>
</annotation>
