<annotation>
	<folder>JPEGImages</folder>
	<filename>1(957)_000004.jpg</filename>
	<path>E:\1\voc_m\JPEGImages\(957).jpg</path>
	<source>
		<database>Unknown</database>
	</source>
	<size>
		<width>640</width>
		<height>640</height>
		<depth>3</depth>
	</size>
	<segmented>0</segmented>
	<object>
		<name>Leaf_Mold</name>
		<pose>Unspecified</pose>
		<truncated>0</truncated>
		<difficult>0</difficult>
		<bndbox>
			<xmin>211</xmin>
			<ymin>367</ymin>
			<xmax>308</xmax>
			<ymax>508</ymax>
		</bndbox>
	</object>
	<object>
		<name>Leaf_Mold</name>
		<pose>Unspecified</pose>
		<truncated>0</truncated>
		<difficult>0</difficult>
		<bndbox>
			<xmin>327</xmin>
			<ymin>162</ymin>
			<xmax>524</xmax>
			<ymax>367</ymax>
		</bndbox>
	</object>
	<object>
		<name>Leaf_Mold</name>
		<pose>Unspecified</pose>
		<truncated>0</truncated>
		<difficult>0</difficult>
		<bndbox>
			<xmin>282</xmin>
			<ymin>369</ymin>
			<xmax>326</xmax>
			<ymax>419</ymax>
		</bndbox>
	</object>
</annotation>