<annotation>
	<folder>JPEGImages</folder>
	<filename>1(233)_000003.jpg</filename>
	<path>G:\1\voc_m\JPEGImages\(233).jpg</path>
	<source>
		<database>Unknown</database>
	</source>
	<size>
		<width>640</width>
		<height>640</height>
		<depth>3</depth>
	</size>
	<segmented>0</segmented>
	<object>
		<name>Early_blight</name>
		<pose>Unspecified</pose>
		<truncated>0</truncated>
		<difficult>0</difficult>
		<bndbox>
			<xmin>286</xmin>
			<ymin>285</ymin>
			<xmax>339</xmax>
			<ymax>342</ymax>
		</bndbox>
	</object>
	<object>
		<name>Early_blight</name>
		<pose>Unspecified</pose>
		<truncated>0</truncated>
		<difficult>0</difficult>
		<bndbox>
			<xmin>197</xmin>
			<ymin>313</ymin>
			<xmax>520</xmax>
			<ymax>607</ymax>
		</bndbox>
	</object>
</annotation>