<annotation>
	<folder>JPEGImages</folder>
	<filename>1(473)_000003.jpg</filename>
	<path>E:\1\voc_m\JPEGImages\(473).jpg</path>
	<source>
		<database>Unknown</database>
	</source>
	<size>
		<width>640</width>
		<height>640</height>
		<depth>3</depth>
	</size>
	<segmented>0</segmented>
	<object>
		<name>Late_blight</name>
		<pose>Unspecified</pose>
		<truncated>0</truncated>
		<difficult>0</difficult>
		<bndbox>
			<xmin>202</xmin>
			<ymin>317</ymin>
			<xmax>305</xmax>
			<ymax>413</ymax>
		</bndbox>
	</object>
	<object>
		<name>Late_blight</name>
		<pose>Unspecified</pose>
		<truncated>0</truncated>
		<difficult>0</difficult>
		<bndbox>
			<xmin>286</xmin>
			<ymin>320</ymin>
			<xmax>307</xmax>
			<ymax>344</ymax>
		</bndbox>
	</object>
	<object>
		<name>Late_blight</name>
		<pose>Unspecified</pose>
		<truncated>0</truncated>
		<difficult>0</difficult>
		<bndbox>
			<xmin>343</xmin>
			<ymin>288</ymin>
			<xmax>373</xmax>
			<ymax>323</ymax>
		</bndbox>
	</object>
	<object>
		<name>Late_blight</name>
		<pose>Unspecified</pose>
		<truncated>0</truncated>
		<difficult>0</difficult>
		<bndbox>
			<xmin>391</xmin>
			<ymin>294</ymin>
			<xmax>485</xmax>
			<ymax>393</ymax>
		</bndbox>
	</object>
	<object>
		<name>Late_blight</name>
		<pose>Unspecified</pose>
		<truncated>0</truncated>
		<difficult>0</difficult>
		<bndbox>
			<xmin>319</xmin>
			<ymin>436</ymin>
			<xmax>479</xmax>
			<ymax>611</ymax>
		</bndbox>
	</object>
	<object>
		<name>healthy</name>
		<pose>Unspecified</pose>
		<truncated>0</truncated>
		<difficult>0</difficult>
		<bndbox>
			<xmin>199</xmin>
			<ymin>44</ymin>
			<xmax>505</xmax>
			<ymax>340</ymax>
		</bndbox>
	</object>
</annotation>