<annotation>
	<folder>JPEGImages</folder>
	<filename>(749).jpg</filename>
	<path>E:\1\voc_m\JPEGImages\(749).jpg</path>
	<source>
		<database>Unknown</database>
	</source>
	<size>
		<width>640</width>
		<height>640</height>
		<depth>3</depth>
	</size>
	<segmented>0</segmented>
	<object>
		<name>healthy</name>
		<pose>Unspecified</pose>
		<truncated>0</truncated>
		<difficult>0</difficult>
		<bndbox>
			<xmin>241</xmin>
			<ymin>89</ymin>
			<xmax>470</xmax>
			<ymax>363</ymax>
		</bndbox>
	</object>
	<object>
		<name>Late_blight</name>
		<pose>Unspecified</pose>
		<truncated>0</truncated>
		<difficult>0</difficult>
		<bndbox>
			<xmin>94</xmin>
			<ymin>282</ymin>
			<xmax>161</xmax>
			<ymax>336</ymax>
		</bndbox>
	</object>
	<object>
		<name>Late_blight</name>
		<pose>Unspecified</pose>
		<truncated>0</truncated>
		<difficult>0</difficult>
		<bndbox>
			<xmin>161</xmin>
			<ymin>263</ymin>
			<xmax>221</xmax>
			<ymax>305</ymax>
		</bndbox>
	</object>
	<object>
		<name>Late_blight</name>
		<pose>Unspecified</pose>
		<truncated>0</truncated>
		<difficult>0</difficult>
		<bndbox>
			<xmin>129</xmin>
			<ymin>216</ymin>
			<xmax>175</xmax>
			<ymax>264</ymax>
		</bndbox>
	</object>
	<object>
		<name>Late_blight</name>
		<pose>Unspecified</pose>
		<truncated>0</truncated>
		<difficult>0</difficult>
		<bndbox>
			<xmin>317</xmin>
			<ymin>446</ymin>
			<xmax>343</xmax>
			<ymax>491</ymax>
		</bndbox>
	</object>
	<object>
		<name>Late_blight</name>
		<pose>Unspecified</pose>
		<truncated>0</truncated>
		<difficult>0</difficult>
		<bndbox>
			<xmin>340</xmin>
			<ymin>360</ymin>
			<xmax>371</xmax>
			<ymax>389</ymax>
		</bndbox>
	</object>
	<object>
		<name>Late_blight</name>
		<pose>Unspecified</pose>
		<truncated>0</truncated>
		<difficult>0</difficult>
		<bndbox>
			<xmin>118</xmin>
			<ymin>299</ymin>
			<xmax>271</xmax>
			<ymax>579</ymax>
		</bndbox>
	</object>
</annotation>
